gavb
