Metadata-Version: 1.0
Name: gavb-nlp
Version: 0.0.3
Summary: NLP preprocessing for different nlp tasks.
Home-page: https://github.com/felipeoliverai/gavb-nlp
Author: Felipe Oliveria / Luiz Simioni / GAVB Deep Learning
Author-email: UNKNOWN
License: MIT
Platform: UNKNOWN
